ray/__init__.py
ray/_raylet.pxd
ray/_raylet.pyi
ray/_raylet.so
ray/actor.py
ray/client_builder.py
ray/cluster_utils.py
ray/cross_language.py
ray/exceptions.py
ray/job_config.py
ray/nightly-wheels.yaml
ray/py.typed
ray/remote_function.py
ray/runtime_context.py
ray/setup-dev.py
ray/types.py
ray/_private/__init__.py
ray/_private/arrow_serialization.py
ray/_private/async_compat.py
ray/_private/auto_init_hook.py
ray/_private/client_mode_hook.py
ray/_private/compat.py
ray/_private/conftest_utils.py
ray/_private/dict.py
ray/_private/external_storage.py
ray/_private/function_manager.py
ray/_private/gcs_pubsub.py
ray/_private/gcs_utils.py
ray/_private/inspect_util.py
ray/_private/internal_api.py
ray/_private/log.py
ray/_private/log_monitor.py
ray/_private/logging_utils.py
ray/_private/memory_monitor.py
ray/_private/metrics_agent.py
ray/_private/node.py
ray/_private/parameter.py
ray/_private/profiling.py
ray/_private/prometheus_exporter.py
ray/_private/ray_client_microbenchmark.py
ray/_private/ray_cluster_perf.py
ray/_private/ray_constants.py
ray/_private/ray_logging.py
ray/_private/ray_microbenchmark_helpers.py
ray/_private/ray_option_utils.py
ray/_private/ray_perf.py
ray/_private/ray_process_reaper.py
ray/_private/resource_spec.py
ray/_private/serialization.py
ray/_private/services.py
ray/_private/signature.py
ray/_private/state.py
ray/_private/state_api_test_utils.py
ray/_private/storage.py
ray/_private/test_utils.py
ray/_private/tls_utils.py
ray/_private/utils.py
ray/_private/worker.py
ray/_private/event/__init__.py
ray/_private/event/event_logger.py
ray/_private/runtime_env/__init__.py
ray/_private/runtime_env/_clonevirtualenv.py
ray/_private/runtime_env/conda.py
ray/_private/runtime_env/conda_utils.py
ray/_private/runtime_env/constants.py
ray/_private/runtime_env/container.py
ray/_private/runtime_env/context.py
ray/_private/runtime_env/java_jars.py
ray/_private/runtime_env/packaging.py
ray/_private/runtime_env/pip.py
ray/_private/runtime_env/plugin.py
ray/thirdparty_files/colorama-0.4.6.dist-info/licenses/LICENSE.txt
ray-2.6.3.dist-info/METADATA
ray-2.6.3.dist-info/WHEEL
ray-2.6.3.dist-info/entry_points.txt
ray-2.6.3.dist-info/top_level.txt
ray/thirdparty_files/colorama-0.4.6.dist-info/INSTALLER
ray/thirdparty_files/colorama-0.4.6.dist-info/METADATA
ray/thirdparty_files/colorama-0.4.6.dist-info/RECORD
ray/thirdparty_files/colorama-0.4.6.dist-info/REQUESTED
ray/thirdparty_files/colorama-0.4.6.dist-info/WHEEL
ray/thirdparty_files/psutil-5.9.5.dist-info/INSTALLER
ray/thirdparty_files/psutil-5.9.5.dist-info/LICENSE
ray/thirdparty_files/psutil-5.9.5.dist-info/METADATA
ray/thirdparty_files/psutil-5.9.5.dist-info/RECORD
ray/thirdparty_files/psutil-5.9.5.dist-info/REQUESTED
ray/thirdparty_files/psutil-5.9.5.dist-info/WHEEL
ray/thirdparty_files/psutil-5.9.5.dist-info/top_level.txt
ray/thirdparty_files/setproctitle-1.2.2.dist-info/INSTALLER
ray/thirdparty_files/setproctitle-1.2.2.dist-info/METADATA
ray/thirdparty_files/setproctitle-1.2.2.dist-info/RECORD
ray/thirdparty_files/setproctitle-1.2.2.dist-info/REQUESTED
ray/thirdparty_files/setproctitle-1.2.2.dist-info/WHEEL
ray/thirdparty_files/setproctitle-1.2.2.dist-info/top_level.txt
ray-2.6.3.dist-info/RECORD
