Metadata-Version: 2.1
Name: ray
Version: 2.6.3
Summary: Ray provides a simple, universal API for building distributed applications.
Home-page: https://github.com/ray-project/ray
Author: Ray Team
Author-email: ray-dev@googlegroups.com
License: Apache 2.0
Keywords: ray distributed parallel machine-learning hyperparameter-tuningreinforcement-learning deep-learning serving python
Classifier: Programming Language :: Python :: 3.7
Classifier: Programming Language :: Python :: 3.8
Classifier: Programming Language :: Python :: 3.9
Classifier: Programming Language :: Python :: 3.10
Requires-Dist: click (>=7.0)
Requires-Dist: filelock
Requires-Dist: jsonschema
Requires-Dist: msgpack (<2.0.0,>=1.0.0)
Requires-Dist: packaging
Requires-Dist: protobuf (!=3.19.5,>=3.15.3)
Requires-Dist: pyyaml
Requires-Dist: aiosignal
Requires-Dist: frozenlist
Requires-Dist: requests
Requires-Dist: grpcio (>=1.32.0) ; python_version < "3.10"
Requires-Dist: typing-extensions ; python_version < "3.8"
Requires-Dist: numpy (>=1.16) ; python_version < "3.9"
Requires-Dist: grpcio (>=1.42.0) ; python_version >= "3.10"
Requires-Dist: numpy (>=1.19.3) ; python_version >= "3.9"
Provides-Extra: air
Requires-Dist: tensorboardX (>=1.9) ; extra == 'air'
Requires-Dist: fsspec ; extra == 'air'
Requires-Dist: pydantic (<2) ; extra == 'air'
Requires-Dist: numpy (>=1.20) ; extra == 'air'
Requires-Dist: aiohttp (>=3.7) ; extra == 'air'
Requires-Dist: smart-open ; extra == 'air'
Requires-Dist: gpustat (>=1.0.0) ; extra == 'air'
Requires-Dist: pandas ; extra == 'air'
Requires-Dist: py-spy (>=0.2.0) ; extra == 'air'
Requires-Dist: opencensus ; extra == 'air'
Requires-Dist: colorful ; extra == 'air'
Requires-Dist: fastapi ; extra == 'air'
Requires-Dist: uvicorn ; extra == 'air'
Requires-Dist: prometheus-client (>=0.7.1) ; extra == 'air'
Requires-Dist: pandas (>=1.3) ; extra == 'air'
Requires-Dist: aiorwlock ; extra == 'air'
Requires-Dist: starlette ; extra == 'air'
Requires-Dist: requests ; extra == 'air'
Requires-Dist: pyarrow (>=6.0.1) ; extra == 'air'
Requires-Dist: aiohttp-cors ; extra == 'air'
Requires-Dist: virtualenv (<20.21.1,>=20.0.24) ; extra == 'air'
Provides-Extra: all
Requires-Dist: tensorboardX (>=1.9) ; extra == 'all'
Requires-Dist: fsspec ; extra == 'all'
Requires-Dist: dm-tree ; extra == 'all'
Requires-Dist: pyyaml ; extra == 'all'
Requires-Dist: pydantic (<2) ; extra == 'all'
Requires-Dist: numpy (>=1.20) ; extra == 'all'
Requires-Dist: aiohttp (>=3.7) ; extra == 'all'
Requires-Dist: smart-open ; extra == 'all'
Requires-Dist: opentelemetry-api ; extra == 'all'
Requires-Dist: ray-cpp (==2.6.3) ; extra == 'all'
Requires-Dist: scipy ; extra == 'all'
Requires-Dist: gpustat (>=1.0.0) ; extra == 'all'
Requires-Dist: pandas ; extra == 'all'
Requires-Dist: rich ; extra == 'all'
Requires-Dist: py-spy (>=0.2.0) ; extra == 'all'
Requires-Dist: opencensus ; extra == 'all'
Requires-Dist: lz4 ; extra == 'all'
Requires-Dist: colorful ; extra == 'all'
Requires-Dist: prometheus-client (>=0.7.1) ; extra == 'all'
Requires-Dist: fastapi ; extra == 'all'
Requires-Dist: uvicorn ; extra == 'all'
Requires-Dist: pandas (>=1.3) ; extra == 'all'
Requires-Dist: aiorwlock ; extra == 'all'
Requires-Dist: starlette ; extra == 'all'
Requires-Dist: opentelemetry-exporter-otlp ; extra == 'all'
Requires-Dist: requests ; extra == 'all'
Requires-Dist: pyarrow (>=6.0.1) ; extra == 'all'
Requires-Dist: typer ; extra == 'all'
Requires-Dist: aiohttp-cors ; extra == 'all'
Requires-Dist: opentelemetry-sdk ; extra == 'all'
Requires-Dist: gymnasium (==0.26.3) ; extra == 'all'
Requires-Dist: virtualenv (<20.21.1,>=20.0.24) ; extra == 'all'
Requires-Dist: grpcio ; extra == 'all'
Requires-Dist: scikit-image ; extra == 'all'
Provides-Extra: client
Requires-Dist: grpcio ; extra == 'client'
Provides-Extra: cpp
Requires-Dist: ray-cpp (==2.6.3) ; extra == 'cpp'
Provides-Extra: data
Requires-Dist: numpy (>=1.20) ; extra == 'data'
Requires-Dist: pandas (>=1.3) ; extra == 'data'
Requires-Dist: pyarrow (>=6.0.1) ; extra == 'data'
Requires-Dist: fsspec ; extra == 'data'
Provides-Extra: default
Requires-Dist: aiohttp (>=3.7) ; extra == 'default'
Requires-Dist: aiohttp-cors ; extra == 'default'
Requires-Dist: colorful ; extra == 'default'
Requires-Dist: py-spy (>=0.2.0) ; extra == 'default'
Requires-Dist: requests ; extra == 'default'
Requires-Dist: gpustat (>=1.0.0) ; extra == 'default'
Requires-Dist: opencensus ; extra == 'default'
Requires-Dist: pydantic (<2) ; extra == 'default'
Requires-Dist: prometheus-client (>=0.7.1) ; extra == 'default'
Requires-Dist: smart-open ; extra == 'default'
Requires-Dist: virtualenv (<20.21.1,>=20.0.24) ; extra == 'default'
Provides-Extra: observability
Requires-Dist: opentelemetry-api ; extra == 'observability'
Requires-Dist: opentelemetry-sdk ; extra == 'observability'
Requires-Dist: opentelemetry-exporter-otlp ; extra == 'observability'
Provides-Extra: rllib
Requires-Dist: pandas ; extra == 'rllib'
Requires-Dist: tensorboardX (>=1.9) ; extra == 'rllib'
Requires-Dist: requests ; extra == 'rllib'
Requires-Dist: pyarrow (>=6.0.1) ; extra == 'rllib'
Requires-Dist: dm-tree ; extra == 'rllib'
Requires-Dist: gymnasium (==0.26.3) ; extra == 'rllib'
Requires-Dist: lz4 ; extra == 'rllib'
Requires-Dist: scikit-image ; extra == 'rllib'
Requires-Dist: pyyaml ; extra == 'rllib'
Requires-Dist: scipy ; extra == 'rllib'
Requires-Dist: typer ; extra == 'rllib'
Requires-Dist: rich ; extra == 'rllib'
Provides-Extra: serve
Requires-Dist: py-spy (>=0.2.0) ; extra == 'serve'
Requires-Dist: opencensus ; extra == 'serve'
Requires-Dist: aiohttp (>=3.7) ; extra == 'serve'
Requires-Dist: smart-open ; extra == 'serve'
Requires-Dist: colorful ; extra == 'serve'
Requires-Dist: fastapi ; extra == 'serve'
Requires-Dist: uvicorn ; extra == 'serve'
Requires-Dist: aiohttp-cors ; extra == 'serve'
Requires-Dist: prometheus-client (>=0.7.1) ; extra == 'serve'
Requires-Dist: gpustat (>=1.0.0) ; extra == 'serve'
Requires-Dist: aiorwlock ; extra == 'serve'
Requires-Dist: starlette ; extra == 'serve'
Requires-Dist: virtualenv (<20.21.1,>=20.0.24) ; extra == 'serve'
Requires-Dist: pydantic (<2) ; extra == 'serve'
Requires-Dist: requests ; extra == 'serve'
Provides-Extra: train
Requires-Dist: pandas ; extra == 'train'
Requires-Dist: tensorboardX (>=1.9) ; extra == 'train'
Requires-Dist: requests ; extra == 'train'
Requires-Dist: pyarrow (>=6.0.1) ; extra == 'train'
Provides-Extra: tune
Requires-Dist: pandas ; extra == 'tune'
Requires-Dist: tensorboardX (>=1.9) ; extra == 'tune'
Requires-Dist: requests ; extra == 'tune'
Requires-Dist: pyarrow (>=6.0.1) ; extra == 'tune'
